pytest_fail_slow/__init__.py
pytest_fail_slow/py.typed
pytest_fail_slow-0.6.0.dist-info/METADATA
pytest_fail_slow-0.6.0.dist-info/WHEEL
pytest_fail_slow-0.6.0.dist-info/entry_points.txt
pytest_fail_slow-0.6.0.dist-info/licenses/LICENSE
pytest_fail_slow-0.6.0.dist-info/RECORD
