Metadata-Version: 2.3
Name: pytest-fail-slow
Version: 0.6.0
Summary: Fail tests that take too long to run
Project-URL: Source Code, https://github.com/jwodder/pytest-fail-slow
Project-URL: Bug Tracker, https://github.com/jwodder/pytest-fail-slow/issues
Author-email: John Thorvald Wodder II <pytest-fail-slow@varonathe.org>
License-Expression: MIT
License-File: LICENSE
Keywords: pytest,slow tests,timeout
Classifier: Environment :: Plugins
Classifier: Framework :: Pytest
Classifier: Intended Audience :: Developers
Classifier: License :: OSI Approved :: MIT License
Classifier: Programming Language :: Python :: 3
Classifier: Programming Language :: Python :: 3 :: Only
Classifier: Programming Language :: Python :: 3.8
Classifier: Programming Language :: Python :: 3.9
Classifier: Programming Language :: Python :: 3.10
Classifier: Programming Language :: Python :: 3.11
Classifier: Programming Language :: Python :: 3.12
Classifier: Programming Language :: Python :: Implementation :: CPython
Classifier: Programming Language :: Python :: Implementation :: PyPy
Classifier: Topic :: Software Development :: Testing
Classifier: Typing :: Typed
Requires-Python: >=3.8
Requires-Dist: pluggy>=1.1
Requires-Dist: pytest>=7.0
